oc_monitor/__init__.py
oc_monitor/data_monitor.py
oc_monitor/html_vis.py
oc_monitor/index_monitor_config.json
oc_monitor/main.py
oc_monitor/meta_monitor_config.json
oc_monitor/old_meta_monitor_config.json
oc_monitor/template.html
oc_monitor-0.1.2.dist-info/LICENSE.md
oc_monitor-0.1.2.dist-info/METADATA
oc_monitor-0.1.2.dist-info/WHEEL
oc_monitor-0.1.2.dist-info/RECORD
