Metadata-Version: 2.3
Name: oc_monitor
Version: 0.1.2
Summary: 
Author: eliarizzetto
Author-email: elia.rizzetto@gmail.com
Requires-Python: >=3.11,<4.0
Classifier: Programming Language :: Python :: 3
Classifier: Programming Language :: Python :: 3.11
Classifier: Programming Language :: Python :: 3.12
Classifier: Programming Language :: Python :: 3.13
Requires-Dist: sparqlwrapper (>=2.0.0,<3.0.0)
